browser_use_undetected/__init__.py
browser_use_undetected/stealth_agent.py
browser_use_undetected/stealth_captcha.py
browser_use_undetected/stealth_session.py
browser_use_undetected/stealth_utils.py
browser_use_undetected/tests/__init__.py
browser_use_undetected/tests/test_imports.py
browser_use_undetected/tests/test_stealth.py
browser_use_undetected-0.2.5.10.dist-info/METADATA
browser_use_undetected-0.2.5.10.dist-info/WHEEL
browser_use_undetected-0.2.5.10.dist-info/licenses/LICENSE
browser_use_undetected-0.2.5.10.dist-info/RECORD
