Metadata-Version: 2.4
Name: browser-use-undetected
Version: 0.2.5.10
Summary: Undetected browser automation addon for browser-use with proxy support
Project-URL: Repository, https://github.com/BARKEM-JC/browser-use-undetected
Author: Jayden Clarke
License-File: LICENSE
Classifier: License :: OSI Approved :: MIT License
Classifier: Operating System :: OS Independent
Classifier: Programming Language :: Python :: 3
Requires-Python: <4.0,>=3.11
Requires-Dist: browser-use>=0.2.5
Requires-Dist: camoufox[geoip]>=0.4.11
Requires-Dist: capsolver>=1.0.0
Requires-Dist: playwright-recaptcha>=0.5.0
Requires-Dist: psutil>=7.0.0
Requires-Dist: pydantic>=2.10.6
